{
  "tank": [{
    "cost": "150",
    "health": "150",
    "damage": "30",
    "velX": "6",
    "velY": "0",
    "range": "600",
    "max health": "250"
  }],
  
  "player": [{
    "health": "250",
    "damage": "50",
    "velX": "3", 
    "velY": "2",
    "range": "480"
    "max health": "250"
  }],
  
  "soldier": [{
    "cost": "50",
    "damage": "1",
    "health": "50",
    "range": "150",
    "velX": "3",
    "velY": "0", 
    "max health": "80"
  }],
  
  "bomb": [{
	"damage": "100",
	"velX": "3",
	"velY": "12"
  }],
  
  "tank shell": [{
  	"velX": "50",
  	"velY": "14"
  }],
  
  "zombie": [{
  	"velX": "-2",
  	"velY": "0",
  	"damage": "1",
  	"range": "150",
  	"health": "50",
    "max health": "80"
  }]
}